[
  { "name": "Grier Rigby", "value": 31.11 },
  { "name": "Kerrie Cotgrove", "value": 66.49 },
  { "name": "Gillie Keatley", "value": 10.19 },
  { "name": "Lane Garces", "value": 43.74 },
  { "name": "Edithe Le Barre", "value": 74.86 },
  { "name": "Verene Crilly", "value": 36.86 },
  { "name": "Karlik Brehat", "value": 42.6 },
  { "name": "Harlan Dinan", "value": 28.69 },
  { "name": "Stella Harwin", "value": 73.75 },
  { "name": "Montague Klagge", "value": 52.24 },
  { "name": "Sayre Heenan", "value": 65.64 },
  { "name": "Court Wilks", "value": 80.17 },
  { "name": "Gnni Tulloch", "value": 7.11 },
  { "name": "Alvinia Haet", "value": 38.69 },
  { "name": "Marnie Barling", "value": 9.42 },
  { "name": "Abramo Fearnall", "value": 11.13 },
  { "name": "Wilhelmina Airds", "value": 26.97 },
  { "name": "Abramo Galtone", "value": 27.98 },
  { "name": "Meir Wanell", "value": 78.8 },
  { "name": "Augustus Carlens", "value": 51.49 },
  { "name": "Carol-jean Mailes", "value": 95.68 },
  { "name": "Markus Aspy", "value": 52.13 },
  { "name": "Link Kimbrough", "value": 36.8 },
  { "name": "Harlene Malletratt", "value": 57.37 },
  { "name": "Dannye Sirett", "value": 48.13 },
  { "name": "Maitilde Sankey", "value": 86.21 },
  { "name": "Ardys Burnard", "value": 20.72 },
  { "name": "Lou Atlay", "value": 19.08 },
  { "name": "Casey Northway", "value": 85.28 },
  { "name": "Rina Saldler", "value": 76.84 },
  { "name": "Cobby Hebbron", "value": 95.01 },
  { "name": "Timmy Toten", "value": 98.07 },
  { "name": "Ilise Tousey", "value": 66.66 },
  { "name": "Christie Phetteplace", "value": 14.85 },
  { "name": "Amelita de Zamora", "value": 60.93 }
]
